nonebot_plugin_delta_helper/__init__.py
nonebot_plugin_delta_helper/config.py
nonebot_plugin_delta_helper/db.py
nonebot_plugin_delta_helper/deltaapi.py
nonebot_plugin_delta_helper/migrations/0ef2cf7a5041_first_revision.py
nonebot_plugin_delta_helper/migrations/3fc264ad0bb7_增加平台类型.py
nonebot_plugin_delta_helper/migrations/7baa1972cb66_增加战绩播报个人开关.py
nonebot_plugin_delta_helper/migrations/dd1ba409cdcc_增加战场战绩播报功能.py
nonebot_plugin_delta_helper/migrations/f9c6a7111d67_add_safe_house_remind_func.py
nonebot_plugin_delta_helper/model.py
nonebot_plugin_delta_helper/render.py
nonebot_plugin_delta_helper/templates/ai_comment.html
nonebot_plugin_delta_helper/templates/base.html
nonebot_plugin_delta_helper/templates/battle_record.html
nonebot_plugin_delta_helper/templates/daily_report.html
nonebot_plugin_delta_helper/templates/help.html
nonebot_plugin_delta_helper/templates/login_success.html
nonebot_plugin_delta_helper/templates/password.html
nonebot_plugin_delta_helper/templates/player_info.html
nonebot_plugin_delta_helper/templates/safehouse.html
nonebot_plugin_delta_helper/templates/single_battle_card.html
nonebot_plugin_delta_helper/templates/single_tdm_card.html
nonebot_plugin_delta_helper/templates/tdm_battle_record.html
nonebot_plugin_delta_helper/templates/weekly_report.html
nonebot_plugin_delta_helper/util.py
nonebot_plugin_delta_helper-0.23.0.dist-info/LICENSE
nonebot_plugin_delta_helper-0.23.0.dist-info/METADATA
nonebot_plugin_delta_helper-0.23.0.dist-info/WHEEL
nonebot_plugin_delta_helper-0.23.0.dist-info/RECORD
