Metadata-Version: 2.3
Name: nonebot-plugin-delta-helper
Version: 0.23.0
Summary: 
License: MIT
Author: Irelia
Author-email: 1074822720@qq.com
Requires-Python: >=3.10,<4.0
Classifier: License :: OSI Approved :: MIT License
Classifier: Programming Language :: Python :: 3
Classifier: Programming Language :: Python :: 3.10
Classifier: Programming Language :: Python :: 3.11
Classifier: Programming Language :: Python :: 3.12
Classifier: Programming Language :: Python :: 3.13
Requires-Dist: httpx (>=0.28.1)
Requires-Dist: jinja2 (>=3.1.6,<4.0.0)
Requires-Dist: nonebot-adapter-onebot (>=2.4.6,<3.0.0)
Requires-Dist: nonebot-plugin-apscheduler (>=0.5.0,<0.6.0)
Requires-Dist: nonebot-plugin-limiter (>=0.2.1,<0.3.0)
Requires-Dist: nonebot-plugin-orm (>=0.8.2,<0.9.0)
Requires-Dist: nonebot-plugin-send-anything-anywhere (>=0.7.1,<0.8.0)
Requires-Dist: nonebot2 (>=2.4.2,<3.0.0)
Requires-Dist: openai (>=1.98.0,<2.0.0)
Requires-Dist: playwright (>=1.54.0,<2.0.0)
Requires-Dist: sqlalchemy (>=2.0.41,<3.0.0)
